stniche/__init__.py
stniche/stniche.py
stniche-0.1.0.dist-info/licenses/LICENSE.txt
stniche-0.1.0.dist-info/METADATA
stniche-0.1.0.dist-info/WHEEL
stniche-0.1.0.dist-info/top_level.txt
stniche-0.1.0.dist-info/RECORD
