Metadata-Version: 2.4
Name: stniche
Version: 0.1.0
Summary: Spatial structure analysis toolkit for transcriptomics.
Home-page: https://github.com/BioinAI/stniche
Author: Mintian Cui
Author-email: 1308318910@qq.com
License: MIT
Classifier: Programming Language :: Python :: 3
Classifier: License :: OSI Approved :: MIT License
Classifier: Operating System :: OS Independent
Classifier: Topic :: Scientific/Engineering :: Bio-Informatics
Requires-Python: >=3.9
License-File: LICENSE.txt
Requires-Dist: pandas<2.1,>=2.0.0
Requires-Dist: numpy<1.23,>=1.22
Requires-Dist: scipy<1.11,>=1.10
Requires-Dist: statsmodels<0.15,>=0.14
Requires-Dist: matplotlib<3.8,>=3.7
Requires-Dist: seaborn<0.14,>=0.13
Requires-Dist: tqdm<4.68,>=4.67
Requires-Dist: scanpy<1.10,>=1.9.8
Requires-Dist: squidpy<1.3,>=1.2
Requires-Dist: plotly<6.1,>=6.0
Requires-Dist: gseapy<1.1,>=1.0
Requires-Dist: kaleido<0.3,>=0.2.1
Dynamic: author
Dynamic: author-email
Dynamic: classifier
Dynamic: description
Dynamic: description-content-type
Dynamic: home-page
Dynamic: license
Dynamic: license-file
Dynamic: requires-dist
Dynamic: requires-python
Dynamic: summary
